<?xml version="1.0" encoding="UTF-8"?>
<jcr:root
    xmlns:sling="http://sling.apache.org/jcr/sling/1.0"
    xmlns:jcr="http://www.jcp.org/jcr/1.0"
    xmlns:cq="http://www.day.com/jcr/cq/1.0"
    xmlns:nt="http://www.jcp.org/jcr/nt/1.0"
    jcr:primaryType="nt:unstructured"
    jcr:title="Template Example Dialog"
    sling:resourceType="cq/gui/components/authoring/dialog">
    <content
        jcr:primaryType="nt:unstructured"
        sling:resourceType="granite/ui/components/coral/foundation/container">
        <items jcr:primaryType="nt:unstructured">
            <tabs
                jcr:primaryType="nt:unstructured"
                sling:resourceType="granite/ui/components/coral/foundation/tabs">
                <items jcr:primaryType="nt:unstructured">
                    <properties
                        jcr:primaryType="nt:unstructured"
                        jcr:title="Cards"
                        sling:resourceType="granite/ui/components/coral/foundation/container">
                        <items jcr:primaryType="nt:unstructured">
                             <layout
                                jcr:primaryType="nt:unstructured"
                                sling:resourceType="granite/ui/components/coral/foundation/form/select"
                                fieldLabel="Card Layout"
                                name="./layout"
                                value="layout1">
                                <items jcr:primaryType="nt:unstructured">
                                    <layout1
                                        jcr:primaryType="nt:unstructured"
                                        text="Layout 1"
                                        value="layout1"/>
                                    <layout2
                                        jcr:primaryType="nt:unstructured"
                                        text="Layout 2"
                                        value="layout2"/>
                                    <layout3
                                        jcr:primaryType="nt:unstructured"
                                        text="Layout 3"
                                        value="layout3"/>
                                    <layout4
                                        jcr:primaryType="nt:unstructured"
                                        text="Layout 4"
                                        value="layout4"/>
                                </items>
                            </layout>
                        </items>
                    </properties>
                </items>
            </tabs>
        </items>
    </content>
</jcr:root>